glog/__init__.py
glog/handler.py
glog/notifier.py
glog_pushover-3.0.5.dist-info/AUTHORS.rst
glog_pushover-3.0.5.dist-info/LICENSE
glog_pushover-3.0.5.dist-info/METADATA
glog_pushover-3.0.5.dist-info/WHEEL
glog_pushover-3.0.5.dist-info/top_level.txt
glog_pushover-3.0.5.dist-info/RECORD
