Metadata-Version: 2.1
Name: glog-pushover
Version: 3.0.5
Summary: A logging system based on structlog with ntfy support
Home-page: https://github.com/Greg0109/glog
Author: Greg Rabago
Author-email: greg.rabago@gmail.com
License: MIT license
Keywords: glog-pushover
Classifier: Development Status :: 2 - Pre-Alpha
Classifier: Intended Audience :: Developers
Classifier: License :: OSI Approved :: MIT License
Classifier: Natural Language :: English
Classifier: Programming Language :: Python :: 3
Classifier: Programming Language :: Python :: 3.6
Classifier: Programming Language :: Python :: 3.7
Classifier: Programming Language :: Python :: 3.8
Requires-Python: >=3.6
License-File: LICENSE
License-File: AUTHORS.rst
